{
    "음소": {
        "C1": "s, m, n, g, b, d, z, gh, bh, dh, mh, zh",
        "V": "u, i, o"
    },
    "예문": {
        "1": "pis tehosas cola sume nut"
    },
    "대명사": {
        "u": "나",
        "o": "타인",
        "i": "인간이 아닌 모든 것"
    },
    "어근": {
        "mogh": "중요, 선호",
        "nudh": "특별",
        "bobh": "정보, 기록",
        "gimh": "논리, 규칙",
        "bhizh": "객관 또는 주관",
        "mhodh": "창조 또는 파괴",
        "sibh": "정신",
        "gobh": "현실, 물리",
        "damh": "학문",
        "zizh": "인간, 윤리",
        
        "biz": "생명력",
        "mhin": "시작 또는 끝",
        "duz": "위치",
        "bud": "변화, 이동",
        "bhos": "사용, 소모",
        "zin": "수용, 저장 또는 방출, 삭제",
        "mid": "행동, -하다",
        "zib": "조작, 조절",
        "sid": "측정",
        
        "nut": "-것",
        "malt": "손, 도구",
        "nult": "장소",

        "s": "현재",
        "d": "과거",
        "h": "미래",
        
        "a": "긍정",
        "u": "부정",
        "e": "중립"
    }
}
